leo_first_mcp_server/__init__.py
leo_first_mcp_server-0.1.4.dist-info/WHEEL
leo_first_mcp_server-0.1.4.dist-info/entry_points.txt
leo_first_mcp_server-0.1.4.dist-info/METADATA
leo_first_mcp_server-0.1.4.dist-info/RECORD
