Metadata-Version: 2.3
Name: leo-first-mcp-server
Version: 0.1.4
Summary: Add your description here
Author: David Lee
Author-email: David Lee <130852499+BaiCai625@users.noreply.github.com>
Requires-Dist: mcp[cli]>=1.12.3
Requires-Python: >=3.13
